jdna/__init__.py
jdna/__version__.py
jdna/align.py
jdna/alphabet.py
jdna/format.py
jdna/interface.py
jdna/io.py
jdna/linked_list.py
jdna/reaction.py
jdna/regions/__init__.py
jdna/regions/context.py
jdna/regions/exceptions.py
jdna/regions/region.py
jdna/sequence.py
jdna/utils.py
jdna/viewer.py
jdna-0.2.dist-info/WHEEL
jdna-0.2.dist-info/METADATA
jdna-0.2.dist-info/RECORD
