Metadata-Version: 2.1
Name: jdna
Version: 0.2
Summary: 
Home-page: https://github.com/jvrana/jdna
Author: Justin Vrana
Author-email: justin.vrana@gmail.com
Requires-Python: >=3.5,<4.0
Classifier: Development Status :: 4 - Beta
Classifier: Intended Audience :: Science/Research
Classifier: Programming Language :: Python :: 3
Classifier: Programming Language :: Python :: 3.5
Classifier: Programming Language :: Python :: 3.6
Classifier: Programming Language :: Python :: 3.7
Classifier: Programming Language :: Python :: 3.8
Classifier: Topic :: Scientific/Engineering :: Bio-Informatics
Requires-Dist: biopython (>=1.73,<2.0)
Requires-Dist: colorama (>=0.4.1,<0.5.0)
Requires-Dist: networkx (>=2.3,<3.0)
Requires-Dist: primer3-py (>=0.6.0,<0.7.0)
Requires-Dist: webcolors (>=1.9,<2.0)
Project-URL: Documentation, https://jvrana.github.io/jdna/
Project-URL: Repository, https://github.com/jvrana/jdna
